LICENSE.md
MANIFEST.in
README.rst
setup.py
ovp_projects/.gitignore
ovp_projects/__init__.py
ovp_projects/apps.py
ovp_projects/decorators.py
ovp_projects/emails.py
ovp_projects/helpers.py
ovp_projects/permissions.py
ovp_projects/urls.py
ovp_projects.egg-info/PKG-INFO
ovp_projects.egg-info/SOURCES.txt
ovp_projects.egg-info/dependency_links.txt
ovp_projects.egg-info/not-zip-safe
ovp_projects.egg-info/requires.txt
ovp_projects.egg-info/top_level.txt
ovp_projects/__pycache__/__init__.cpython-35.pyc
ovp_projects/__pycache__/apps.cpython-35.pyc
ovp_projects/__pycache__/decorators.cpython-35.pyc
ovp_projects/__pycache__/emails.cpython-35.pyc
ovp_projects/__pycache__/helpers.cpython-35.pyc
ovp_projects/__pycache__/permissions.cpython-35.pyc
ovp_projects/__pycache__/urls.cpython-35.pyc
ovp_projects/admin/__init__.py
ovp_projects/admin/apply.py
ovp_projects/admin/job.py
ovp_projects/admin/jobdate.py
ovp_projects/admin/project.py
ovp_projects/admin/work.py
ovp_projects/admin/__pycache__/__init__.cpython-35.pyc
ovp_projects/admin/__pycache__/apply.cpython-35.pyc
ovp_projects/admin/__pycache__/job.cpython-35.pyc
ovp_projects/admin/__pycache__/jobdate.cpython-35.pyc
ovp_projects/admin/__pycache__/project.cpython-35.pyc
ovp_projects/admin/__pycache__/work.cpython-35.pyc
ovp_projects/locale/pt_BR/LC_MESSAGES/django.mo
ovp_projects/locale/pt_BR/LC_MESSAGES/django.po
ovp_projects/management/__init__.py
ovp_projects/management/__pycache__/__init__.cpython-35.pyc
ovp_projects/management/commands/__init__.py
ovp_projects/management/commands/close_finished_projects.py
ovp_projects/management/commands/__pycache__/__init__.cpython-35.pyc
ovp_projects/management/commands/__pycache__/close_finished_projects.cpython-35.pyc
ovp_projects/migrations/0001_initial.py
ovp_projects/migrations/0002_auto_20161019_1557.py
ovp_projects/migrations/0003_auto_20161025_1609.py
ovp_projects/migrations/0004_auto_20161025_1626.py
ovp_projects/migrations/0005_auto_20161025_1627.py
ovp_projects/migrations/0006_auto_20161025_1726.py
ovp_projects/migrations/0007_project_image.py
ovp_projects/migrations/0008_project_organization.py
ovp_projects/migrations/0009_auto_20161102_2122.py
