Metadata-Version: 1.1
Name: ovp-projects
Version: 1.2.12
Summary: This module has core functionality for ovp projects, such as creation, editing and retrieving.
Home-page: https://github.com/OpenVolunteeringPlatform/django-ovp-projects
Author: Atados
Author-email: arroyo@atados.com.br
License: AGPL
Download-URL: https://github.com/OpenVolunteeringPlatform/django-ovp-projects/tarball/1.2.12
Platform: UNKNOWN
